fancy_print/__init__.py
fancy_print/fprint.py
fancy_print/test.py
yaol_utils-0.0.2.dist-info/LICENSE
yaol_utils-0.0.2.dist-info/METADATA
yaol_utils-0.0.2.dist-info/WHEEL
yaol_utils-0.0.2.dist-info/top_level.txt
yaol_utils-0.0.2.dist-info/RECORD
