Metadata-Version: 2.1
Name: yaol-utils
Version: 0.0.2
Summary: Some helpful utility functions
Author: Phillip Yao-Lakaschus
Author-email: <Philliplakaschus@gmail.com>
License: UNKNOWN
Keywords: python,util,utils,print
Platform: UNKNOWN
Classifier: Development Status :: 1 - Planning
Classifier: Intended Audience :: Developers
Classifier: Programming Language :: Python :: 3
Classifier: Operating System :: Unix
Classifier: Operating System :: MacOS :: MacOS X
Classifier: Operating System :: Microsoft :: Windows
License-File: LICENSE
Requires-Dist: varname
